model_admin/__init__.py
model_admin/__version__.py
model_admin/apps.py
model_admin/hooks/__init__.py
model_admin/hooks/buttons/__init__.py
model_admin/hooks/buttons/actions/__init__.py
model_admin/hooks/buttons/actions/duplicate.py
model_admin/hooks/buttons/components/__init__.py
model_admin/hooks/buttons/components/add.py
model_admin/hooks/buttons/components/button.py
model_admin/hooks/buttons/components/delete.py
model_admin/hooks/buttons/components/duplicate.py
model_admin/hooks/buttons/components/edit.py
model_admin/hooks/buttons/components/inspect.py
model_admin/hooks/buttons/entity/__init__.py
model_admin/hooks/buttons/entity/button.py
model_admin/hooks/buttons/handlers/__init__.py
model_admin/hooks/buttons/handlers/field_handler.py
model_admin/hooks/buttons/handlers/register_handlers.py
model_admin/hooks/buttons/handlers/slug_field_handler.py
model_admin/hooks/buttons/helpers/__init__.py
model_admin/hooks/buttons/helpers/base_button_helper.py
model_admin/hooks/buttons/helpers/default_button_helper.py
model_admin/hooks/modeladmin/__init__.py
model_admin/hooks/modeladmin/base_model_admin.py
model_admin/hooks/views/__init__.py
model_admin/hooks/views/duplicate.py
model_admin/templates/modeladmin/duplicate.html
model_admin/tests/__init__.py
model_admin/tests/hooks/__init__.py
model_admin/tests/hooks/buttons/__init__.py
model_admin/tests/hooks/buttons/actions/__init__.py
model_admin/tests/hooks/buttons/actions/test_duplicate.py
model_admin/tests/hooks/buttons/components/__init__.py
model_admin/tests/hooks/buttons/components/test_delete.py
model_admin/tests/hooks/buttons/handlers/__init__.py
model_admin/tests/hooks/buttons/handlers/test_handler.py
model_admin/tests/hooks/buttons/handlers/test_register_handler.py
model_admin/tests/hooks/buttons/helpers/__init__.py
model_admin/tests/hooks/buttons/helpers/test_base.py
model_admin/tests/hooks/buttons/test_base/__init__.py
model_admin/tests/hooks/buttons/test_base/base.py
wagtail_modeladmin_extension-0.1.15.dist-info/LICENSE
wagtail_modeladmin_extension-0.1.15.dist-info/METADATA
wagtail_modeladmin_extension-0.1.15.dist-info/WHEEL
wagtail_modeladmin_extension-0.1.15.dist-info/top_level.txt
wagtail_modeladmin_extension-0.1.15.dist-info/RECORD
